slack_blocks_markdown/__init__.py
slack_blocks_markdown/blocks.py
slack_blocks_markdown/py.typed
slack_blocks_markdown/renderer.py
slack_blocks_markdown-0.2.1.dist-info/licenses/LICENSE
slack_blocks_markdown-0.2.1.dist-info/METADATA
slack_blocks_markdown-0.2.1.dist-info/WHEEL
slack_blocks_markdown-0.2.1.dist-info/top_level.txt
slack_blocks_markdown-0.2.1.dist-info/RECORD
