Metadata-Version: 2.4
Name: slack-blocks-markdown
Version: 0.2.1
Summary: Convert Markdown to Slack Block Kit blocks using mistletoe
Author-email: atacan <info@actondon.com>
Maintainer-email: atacan <info@actondon.com>
License: MIT License
Project-URL: Homepage, https://github.com/atacan/slack-blocks-markdown
Project-URL: Repository, https://github.com/atacan/slack-blocks-markdown
Project-URL: Issues, https://github.com/atacan/slack-blocks-markdown/issues
Project-URL: Documentation, https://github.com/atacan/slack-blocks-markdown/blob/main/README.md
Keywords: slack,markdown,blocks,mistletoe,converter,block-kit
Classifier: Development Status :: 4 - Beta
Classifier: Intended Audience :: Developers
Classifier: Programming Language :: Python :: 3
Classifier: Programming Language :: Python :: 3.11
Classifier: Programming Language :: Python :: 3.12
Classifier: Programming Language :: Python :: 3.13
Classifier: Topic :: Communications :: Chat
Classifier: Topic :: Text Processing :: Markup
Classifier: Topic :: Software Development :: Libraries :: Python Modules
Requires-Python: >=3.11
License-File: LICENSE
Requires-Dist: mistletoe>=1.4.0
Requires-Dist: slack-sdk>=3.36.0
Provides-Extra: dev
Requires-Dist: pytest>=7.4.0; extra == "dev"
Requires-Dist: pytest-cov>=4.1.0; extra == "dev"
Requires-Dist: black>=23.0.0; extra == "dev"
Requires-Dist: ruff>=0.1.0; extra == "dev"
Requires-Dist: mypy>=1.5.0; extra == "dev"
Requires-Dist: pre-commit>=3.0.0; extra == "dev"
Provides-Extra: test
Requires-Dist: pytest>=7.4.0; extra == "test"
Requires-Dist: pytest-cov>=4.1.0; extra == "test"
Dynamic: license-file
